[
  {
    "sofascoreId": 974747,
    "club": "Al-Wehdat",
    "marketValueEur": 240000,
    "marketValueDisplay": "€240K",
    "dateOfBirth": "2000-01-22",
    "age": 26,
    "internationalCaps": null,
    "internationalGoals": null
  },
  {
    "sofascoreId": 828259,
    "club": "Al Faisaly SC",
    "marketValueEur": 260000,
    "marketValueDisplay": "€260K",
    "dateOfBirth": "1993-01-25",
    "age": 33,
    "internationalCaps": null,
    "internationalGoals": null
  },
  {
    "sofascoreId": 828294,
    "club": "Al-Hussein Irbid",
    "marketValueEur": 290000,
    "marketValueDisplay": "€290K",
    "dateOfBirth": "1993-01-08",
    "age": 33,
    "internationalCaps": null,
    "internationalGoals": null
  },
  {
    "sofascoreId": 1114497,
    "club": "Al-Zawraa",
    "marketValueEur": 450000,
    "marketValueDisplay": "€450K",
    "dateOfBirth": "1994-02-25",
    "age": 32,
    "internationalCaps": null,
    "internationalGoals": null
  },
  {
    "sofascoreId": 2239188,
    "club": "Al Faisaly SC",
    "marketValueEur": 180000,
    "marketValueDisplay": "€180K",
    "dateOfBirth": "1997-09-13",
    "age": 28,
    "internationalCaps": null,
    "internationalGoals": null
  },
  {
    "sofascoreId": 1122369,
    "club": "Al Faisaly SC",
    "marketValueEur": 330000,
    "marketValueDisplay": "€330K",
    "dateOfBirth": "2000-05-13",
    "age": 26,
    "internationalCaps": null,
    "internationalGoals": null
  },
  {
    "sofascoreId": 1158813,
    "club": "FC Corvinul Hunedoara",
    "marketValueEur": 380000,
    "marketValueDisplay": "€380K",
    "dateOfBirth": "2001-02-08",
    "age": 25,
    "internationalCaps": null,
    "internationalGoals": null
  },
  {
    "sofascoreId": 1139989,
    "club": "Al Karma SC",
    "marketValueEur": 440000,
    "marketValueDisplay": "€440K",
    "dateOfBirth": "1995-05-09",
    "age": 31,
    "internationalCaps": null,
    "internationalGoals": null
  },
  {
    "sofascoreId": 2048339,
    "club": "Al-Hussein Irbid",
    "marketValueEur": 260000,
    "marketValueDisplay": "€260K",
    "dateOfBirth": "2005-07-13",
    "age": 20,
    "internationalCaps": null,
    "internationalGoals": null
  },
  {
    "sofascoreId": 920476,
    "club": "Al-Hussein Irbid",
    "marketValueEur": 390000,
    "marketValueDisplay": "€390K",
    "dateOfBirth": "1997-02-01",
    "age": 29,
    "internationalCaps": null,
    "internationalGoals": null
  },
  {
    "sofascoreId": 980664,
    "club": "Al-Hussein Irbid",
    "marketValueEur": 97000,
    "marketValueDisplay": "€97K",
    "dateOfBirth": "1992-01-17",
    "age": 34,
    "internationalCaps": null,
    "internationalGoals": null
  },
  {
    "sofascoreId": 888906,
    "club": "FC Seoul",
    "marketValueEur": 1000000,
    "marketValueDisplay": "€1M",
    "dateOfBirth": "1996-01-31",
    "age": 30,
    "internationalCaps": null,
    "internationalGoals": null
  },
  {
    "sofascoreId": 1457997,
    "club": "Al-Shabab",
    "marketValueEur": 210000,
    "marketValueDisplay": "€210K",
    "dateOfBirth": "2004-04-13",
    "age": 22,
    "internationalCaps": null,
    "internationalGoals": null
  },
  {
    "sofascoreId": 1019495,
    "club": "Al-Zawraa",
    "marketValueEur": 435000,
    "marketValueDisplay": "€435K",
    "dateOfBirth": "2002-07-03",
    "age": 23,
    "internationalCaps": null,
    "internationalGoals": null
  },
  {
    "sofascoreId": 812997,
    "club": "Al-Hussein Irbid",
    "marketValueEur": 340000,
    "marketValueDisplay": "€340K",
    "dateOfBirth": "1994-02-05",
    "age": 32,
    "internationalCaps": null,
    "internationalGoals": null
  },
  {
    "sofascoreId": 997817,
    "club": "Al Karma SC",
    "marketValueEur": 415000,
    "marketValueDisplay": "€415K",
    "dateOfBirth": "2000-04-26",
    "age": 26,
    "internationalCaps": null,
    "internationalGoals": null
  },
  {
    "sofascoreId": 812557,
    "club": "Al-Hussein Irbid",
    "marketValueEur": 390000,
    "marketValueDisplay": "€390K",
    "dateOfBirth": "1993-10-06",
    "age": 32,
    "internationalCaps": null,
    "internationalGoals": null
  },
  {
    "sofascoreId": 986341,
    "club": "Raja Club Athletic",
    "marketValueEur": 400000,
    "marketValueDisplay": "€400K",
    "dateOfBirth": "1997-12-30",
    "age": 28,
    "internationalCaps": null,
    "internationalGoals": null
  },
  {
    "sofascoreId": 786034,
    "club": "Al-Wehdat",
    "marketValueEur": 160000,
    "marketValueDisplay": "€160K",
    "dateOfBirth": "1992-04-12",
    "age": 34,
    "internationalCaps": null,
    "internationalGoals": null
  },
  {
    "sofascoreId": 1114775,
    "club": "Al-Quwa Al-Jawiya",
    "marketValueEur": 440000,
    "marketValueDisplay": "€440K",
    "dateOfBirth": "2003-02-02",
    "age": 23,
    "internationalCaps": null,
    "internationalGoals": null
  },
  {
    "sofascoreId": 1014324,
    "club": "Qatar SC",
    "marketValueEur": 620000,
    "marketValueDisplay": "€620K",
    "dateOfBirth": "1999-03-23",
    "age": 27,
    "internationalCaps": null,
    "internationalGoals": null
  },
  {
    "sofascoreId": 927845,
    "club": "Selangor FC",
    "marketValueEur": 455000,
    "marketValueDisplay": "€455K",
    "dateOfBirth": "1997-02-24",
    "age": 29,
    "internationalCaps": null,
    "internationalGoals": null
  },
  {
    "sofascoreId": 786030,
    "club": "Al-Hussein Irbid",
    "marketValueEur": 320000,
    "marketValueDisplay": "€320K",
    "dateOfBirth": "1993-07-25",
    "age": 32,
    "internationalCaps": null,
    "internationalGoals": null
  },
  {
    "sofascoreId": 980728,
    "club": "Al-Sailiya",
    "marketValueEur": 825000,
    "marketValueDisplay": "€825K",
    "dateOfBirth": "2000-03-26",
    "age": 26,
    "internationalCaps": null,
    "internationalGoals": null
  },
  {
    "sofascoreId": 876600,
    "club": "Stade Rennais",
    "marketValueEur": 10800000,
    "marketValueDisplay": "€10.8M",
    "dateOfBirth": "1997-06-10",
    "age": 29,
    "internationalCaps": null,
    "internationalGoals": null
  },
  {
    "sofascoreId": 1937497,
    "club": "Pyramids FC",
    "marketValueEur": 225000,
    "marketValueDisplay": "€225K",
    "dateOfBirth": "2005-11-20",
    "age": 20,
    "internationalCaps": null,
    "internationalGoals": null
  }
]